hacli/__init__.py
hacli/apis/__init__.py
hacli/apis/apis.py
hacli/apis/core/__init__.py
hacli/apis/core/config.py
hacli/apis/register/__init__.py
hacli/apis/register/exception.py
hacli/apis/register/router.py
hacli/apis/router/__init__.py
hacli/apis/router/deploy.py
hacli/apis/router/git.py
hacli/apis/router/image.py
hacli/apis/router/release.py
hacli/apis/router/tag.py
hacli/apis/schemas/__init__.py
hacli/apis/schemas/deploy_models.py
hacli/apis/schemas/git_models.py
hacli/deploy/__init__.py
hacli/deploy/build_up_inactive_cluster.py
hacli/deploy/check_services_deployment_status.py
hacli/deploy/deploy_inactive_services.py
hacli/deploy/deploy_inactive_shared_services.py
hacli/deploy/sync_global_repo.py
hacli/deploy/teardown_inactive_cluster.py
hacli/deploy/toggle_active_cluster.py
hacli/deploy/update_active_service_config.py
hacli/git/__init__.py
hacli/git/git_ops.py
hacli/image/__init__.py
hacli/image/check_service_image_imported.py
hacli/image/import_global_external_images.py
hacli/image/import_global_service_images.py
hacli/image/purge_local_images.py
hacli/main.py
hacli/release/__init__.py
hacli/release/configuration_change_list.py
hacli/release/create_release_note_email_content.py
hacli/release/create_release_note_md.py
hacli/release/release_checkout_date.py
hacli/tag/__init__.py
hacli/tag/get_global_rollout_status.py
hacli/utils/__init__.py
hacli/utils/ado.py
hacli/utils/envs.py
hacli/utils/git_commands.py
hacli-0.7.10.dist-info/METADATA
hacli-0.7.10.dist-info/WHEEL
hacli-0.7.10.dist-info/entry_points.txt
hacli-0.7.10.dist-info/RECORD
