Metadata-Version: 2.3
Name: hacli
Version: 0.7.10
Summary: 
Author: codehamal
Author-email: codehamal@example.com
Requires-Python: >=3.9.0
Classifier: Programming Language :: Python :: 3
Classifier: Programming Language :: Python :: 3.9
Classifier: Programming Language :: Python :: 3.10
Classifier: Programming Language :: Python :: 3.11
Classifier: Programming Language :: Python :: 3.12
Classifier: Programming Language :: Python :: 3.13
Requires-Dist: azure-containerregistry (>=1.2.0,<2.0.0)
Requires-Dist: azure-devops (>=7.1.0b4,<8.0.0)
Requires-Dist: azure-identity (>=1.20.0,<2.0.0)
Requires-Dist: azure-keyvault-secrets (>=4.9.0,<5.0.0)
Requires-Dist: beautifulsoup4 (>=4.13.3,<5.0.0)
Requires-Dist: fastapi (>=0.115.8,<0.116.0)
Requires-Dist: gitpython (>=3.1.44,<4.0.0)
Requires-Dist: html2text (>=2024.2.26,<2025.0.0)
Requires-Dist: markdown-it-py (>=3.0.0,<4.0.0)
Requires-Dist: prettytable (>=3.15.1,<4.0.0)
Requires-Dist: pydantic (>=2.10.6,<3.0.0)
Requires-Dist: pydantic-settings (>=2.8.1,<3.0.0)
Requires-Dist: pyyaml (>=6.0.2,<7.0.0)
Requires-Dist: tabulate (>=0.9.0,<0.10.0)
Requires-Dist: typer (>=0.15.1,<0.16.0)
Requires-Dist: uvicorn (>=0.34.0,<0.35.0)
